hyapi/__init__.py
hyapi/api.py
hyapi/auth.py
hyapi/error.py
hyapi/pkcs7.py
hyapi-0.0.1.dist-info/DESCRIPTION.rst
hyapi-0.0.1.dist-info/METADATA
hyapi-0.0.1.dist-info/metadata.json
hyapi-0.0.1.dist-info/pbr.json
hyapi-0.0.1.dist-info/RECORD
hyapi-0.0.1.dist-info/top_level.txt
hyapi-0.0.1.dist-info/WHEEL
hyauth/__init__.py
hyauth/api.py
hyauth/auth.py
hyauth/error.py
hyauth/pkcs7.py
