Metadata-Version: 2.0
Name: hyapi
Version: 0.0.1
Summary: Python SDK for Hanyang Univ API
Home-page: http://github.com/kimtree/hyapi
Author: Namwoo Kim
Author-email: kimtree@hanyang.ac.kr
License: MIT
Keywords: hanyang university
Platform: UNKNOWN
Classifier: Development Status :: 2 - Pre-Alpha
Classifier: Topic :: Software Development :: Libraries
Classifier: Operating System :: OS Independent
Classifier: License :: OSI Approved :: MIT License
Classifier: Programming Language :: Python
Classifier: Programming Language :: Python :: 2
Classifier: Programming Language :: Python :: 2.6
Classifier: Programming Language :: Python :: 2.7
Requires-Dist: pycrypto (==2.6.1)
Requires-Dist: requests (==2.6.0)
